kirpich_environs/__init__.py
kirpich_environs/environs.py
kirpich_environs-0.0.2.dist-info/LICENSE
kirpich_environs-0.0.2.dist-info/METADATA
kirpich_environs-0.0.2.dist-info/WHEEL
kirpich_environs-0.0.2.dist-info/top_level.txt
kirpich_environs-0.0.2.dist-info/RECORD
